sphinxcontrib_contentui-0.2.4-py3.6-nspkg.pth
sphinxcontrib/contentui.css
sphinxcontrib/contentui.js
sphinxcontrib/contentui.py
sphinxcontrib_contentui-0.2.4.dist-info/METADATA
sphinxcontrib_contentui-0.2.4.dist-info/WHEEL
sphinxcontrib_contentui-0.2.4.dist-info/namespace_packages.txt
sphinxcontrib_contentui-0.2.4.dist-info/top_level.txt
sphinxcontrib_contentui-0.2.4.dist-info/RECORD
