Metadata-Version: 2.1
Name: sphinxcontrib-contentui
Version: 0.2.4
Summary: Sphinx "contentui" extension
Home-page: https://github.com/ulrobix/sphinxcontrib-contentui
Author: Robert Khaliullov
Author-email: ulrobix@gmail.com
License: BSD
Download-URL: http://pypi.python.org/pypi/sphinxcontrib-contentui
Platform: any
Classifier: Development Status :: 4 - Beta
Classifier: Environment :: Console
Classifier: Environment :: Web Environment
Classifier: Intended Audience :: Developers
Classifier: License :: OSI Approved :: BSD License
Classifier: Operating System :: OS Independent
Classifier: Programming Language :: Python
Classifier: Topic :: Documentation
Classifier: Topic :: Utilities
Requires-Dist: Sphinx (>=2.0)
